pyter/__init__.py
pyter3-0.3.dist-info/METADATA
pyter3-0.3.dist-info/WHEEL
pyter3-0.3.dist-info/top_level.txt
pyter3-0.3.dist-info/RECORD
