Metadata-Version: 2.1
Name: pyter3
Version: 0.3
Summary: Simple library to evaluate the Translation Edit Rate
Home-page: https://github.com/BramVanroy/pyter
Author: Hiroyuki Tanaka, Bram Vanroy
Author-email: afl0x@gmail.com
License: MIT
Platform: UNKNOWN
Classifier: Development Status :: 4 - Beta
Classifier: Intended Audience :: Information Technology
Classifier: Intended Audience :: End Users/Desktop
Classifier: Intended Audience :: Developers
Classifier: Intended Audience :: Science/Research
Classifier: License :: OSI Approved :: MIT License
Classifier: Programming Language :: Python
Classifier: Programming Language :: Python :: 3
Classifier: Topic :: Text Processing
